sscreen/__init__.py
sscreen/utils.py
sscreen/widgets.py
sscreen/window.py
sscreen-0.2.dist-info/METADATA
sscreen-0.2.dist-info/WHEEL
sscreen-0.2.dist-info/top_level.txt
sscreen-0.2.dist-info/RECORD
