Metadata-Version: 2.4
Name: sscreen
Version: 0.2
Summary: A modern PyQt6 GUI library
Home-page: 
Author: Sanki
Classifier: Programming Language :: Python :: 3
Classifier: License :: OSI Approved :: MIT License
Classifier: Operating System :: OS Independent
Requires-Dist: PyQt6
Dynamic: author
Dynamic: classifier
Dynamic: description
Dynamic: description-content-type
Dynamic: requires-dist
Dynamic: summary
